tkface/__init__.py
tkface/dialog/__init__.py
tkface/dialog/datepicker.py
tkface/dialog/messagebox.py
tkface/dialog/pathchooser.py
tkface/dialog/simpledialog.py
tkface/dialog/timepicker.py
tkface/lang/__init__.py
tkface/lang/lang.py
tkface/locales/en.msg
tkface/locales/ja.msg
tkface/themes/dark.ini
tkface/themes/light.ini
tkface/widget/__init__.py
tkface/widget/timespinner.py
tkface/widget/calendar/__init__.py
tkface/widget/calendar/core.py
tkface/widget/calendar/style.py
tkface/widget/calendar/view.py
tkface/widget/pathbrowser/__init__.py
tkface/widget/pathbrowser/core.py
tkface/widget/pathbrowser/manager.py
tkface/widget/pathbrowser/style.py
tkface/widget/pathbrowser/utils.py
tkface/widget/pathbrowser/view.py
tkface/win/__init__.py
tkface/win/bell.py
tkface/win/button.py
tkface/win/dpi.py
tkface/win/unround.py
tkface-0.2.0.dist-info/licenses/LICENSE
tkface-0.2.0.dist-info/METADATA
tkface-0.2.0.dist-info/WHEEL
tkface-0.2.0.dist-info/top_level.txt
tkface-0.2.0.dist-info/RECORD
