Metadata-Version: 2.4
Name: tkface
Version: 0.2.0
Summary: A comprehensive multilingual GUI extension library for Tkinter with enhanced message boxes, calendar widgets, theme system, and Windows-specific features
Author: mashu3
License-Expression: MIT
Project-URL: Homepage, https://github.com/mashu3/tkface
Project-URL: Repository, https://github.com/mashu3/tkface
Project-URL: Documentation, https://github.com/mashu3/tkface#readme
Project-URL: Bug Tracker, https://github.com/mashu3/tkface/issues
Keywords: tkinter,gui,multilingual,internationalization,messagebox,dialog,calendar,theme,windows
Classifier: Development Status :: 4 - Beta
Classifier: Intended Audience :: Developers
Classifier: Operating System :: OS Independent
Classifier: Programming Language :: Python :: 3
Classifier: Programming Language :: Python :: 3.7
Classifier: Programming Language :: Python :: 3.8
Classifier: Programming Language :: Python :: 3.9
Classifier: Programming Language :: Python :: 3.10
Classifier: Programming Language :: Python :: 3.11
Classifier: Programming Language :: Python :: 3.12
Classifier: Programming Language :: Python :: 3.13
Classifier: Topic :: Software Development :: Libraries :: Python Modules
Classifier: Topic :: Software Development :: User Interfaces
Classifier: Topic :: Software Development :: Internationalization
Requires-Python: >=3.7
License-File: LICENSE
Provides-Extra: dev
Requires-Dist: black>=21.0; extra == "dev"
Requires-Dist: flake8>=3.8; extra == "dev"
Dynamic: license-file
